<?xml version="1.0" encoding="iso-8859-1" standalone="no" ?>
<TV_Version>

	<CREATED>
		<DATE>27.04.2018</DATE>
		<TIME>09:07:00</TIME>
	</CREATED>

	<VERSION>
		<HDSDLL>1.0.1.0</HDSDLL>
	</VERSION>

	<CHANGES>Init</CHANGES>

	<FILES>
		<FILE>
			<NAME>dh_hdsconverter.dll</NAME>
			<MD5>04F354C4F9AAB129F873E691AB5C3FD5</MD5>
			<SUBDIR></SUBDIR>
			<SIZE>39672</SIZE>
		</FILE>
		<FILE>
			<NAME>dh_hdsdatamodel.dll</NAME>
			<MD5>19486029F25047FED0D3A1C464E82C78</MD5>
			<SUBDIR></SUBDIR>
			<SIZE>43768</SIZE>
		</FILE>
		<FILE>
			<NAME>dh_hdsencryptor.dll</NAME>
			<MD5>5EB2412D52ABC2869DCD17EAE64E9850</MD5>
			<SUBDIR></SUBDIR>
			<SIZE>1123064</SIZE>
		</FILE>
		<FILE>
			<NAME>dh_hdsimg.dll</NAME>
			<MD5>8AC951788854B5B510FB2DE7C75EADA5</MD5>
			<SUBDIR></SUBDIR>
			<SIZE>4050168</SIZE>
		</FILE>
		<FILE>
			<NAME>dh_hdsmeta.dll</NAME>
			<MD5>74D1B42C6D5B246154290B490B5B90C0</MD5>
			<SUBDIR></SUBDIR>
			<SIZE>276216</SIZE>
		</FILE>
		<FILE>
			<NAME>dh_hdsportalapi.dll</NAME>
			<MD5>067C7EA59DF8858E2B2FDD173274712E</MD5>
			<SUBDIR></SUBDIR>
			<SIZE>370936</SIZE>
		</FILE>
		<FILE>
			<NAME>dh_hdstool.dll</NAME>
			<MD5>BC60C808618A7A4B3AA1079D18DC9E52</MD5>
			<SUBDIR></SUBDIR>
			<SIZE>134904</SIZE>
		</FILE>
		<FILE>
			<NAME>HDS.dll</NAME>
			<MD5>C2994CE4FA3C68EA92E85756F8D6FDF7</MD5>
			<SUBDIR></SUBDIR>
			<SIZE>80120</SIZE>
		</FILE>
		<FILE>
			<NAME>HDSLib.xml</NAME>
			<MD5>C5F6D62E962608DF500C7BD82A296A3E</MD5>
			<SUBDIR></SUBDIR>
			<SIZE>2746</SIZE>
		</FILE>
		<FILE>
			<NAME>HDSLibServer.xml</NAME>
			<MD5>C5F6D62E962608DF500C7BD82A296A3E</MD5>
			<SUBDIR></SUBDIR>
			<SIZE>2746</SIZE>
		</FILE>
		<FILE>
			<NAME>icudt53.dll</NAME>
			<MD5>AFF9A68D74E5B9BA909426EC4AAF3D0D</MD5>
			<SUBDIR></SUBDIR>
			<SIZE>855288</SIZE>
		</FILE>
		<FILE>
			<NAME>icuin53.dll</NAME>
			<MD5>977B4ABE14E8F081E62D6D2ECC1AF63B</MD5>
			<SUBDIR></SUBDIR>
			<SIZE>1989368</SIZE>
		</FILE>
		<FILE>
			<NAME>icuuc53.dll</NAME>
			<MD5>CF4CC5F73C038D6ED96C94D5829C8B4C</MD5>
			<SUBDIR></SUBDIR>
			<SIZE>1361656</SIZE>
		</FILE>
		<FILE>
			<NAME>libeay32.dll</NAME>
			<MD5>808C6EBBB8BCD4C15E671F0C481D9CD6</MD5>
			<SUBDIR></SUBDIR>
			<SIZE>1183480</SIZE>
		</FILE>
		<FILE>
			<NAME>Qt5Core.dll</NAME>
			<MD5>D4F63D7F76B24E25F04A9C81D12E42CA</MD5>
			<SUBDIR></SUBDIR>
			<SIZE>4057848</SIZE>
		</FILE>
		<FILE>
			<NAME>Qt5Network.dll</NAME>
			<MD5>6D6600DFD715067D2461F88699D755AF</MD5>
			<SUBDIR></SUBDIR>
			<SIZE>825080</SIZE>
		</FILE>
		<FILE>
			<NAME>quazip1.dll</NAME>
			<MD5>EF5FCC944EE692FEF9BB6DF760F2C459</MD5>
			<SUBDIR></SUBDIR>
			<SIZE>115960</SIZE>
		</FILE>
		<FILE>
			<NAME>ssleay32.dll</NAME>
			<MD5>9C32E575E5553506937CC3CCC6586A0C</MD5>
			<SUBDIR></SUBDIR>
			<SIZE>273144</SIZE>
		</FILE>
		<FILE>
			<NAME>zlib1.dll</NAME>
			<MD5>CEBACEAC5B5664836E0F5839A0BD10A0</MD5>
			<SUBDIR></SUBDIR>
			<SIZE>78584</SIZE>
		</FILE>
		<FILE>
			<NAME>HDSLib.xml</NAME>
			<MD5></MD5>
			<SUBDIR></SUBDIR>
			<SIZE></SIZE>
		</FILE>
	</FILES>
</TV_Version>

